git_grab/__init__.py
git_grab/cli.py
git_grab-0.7.0.dist-info/LICENSE
git_grab-0.7.0.dist-info/METADATA
git_grab-0.7.0.dist-info/WHEEL
git_grab-0.7.0.dist-info/entry_points.txt
git_grab-0.7.0.dist-info/RECORD
